<?xml version="1.0" encoding="utf-8"?>
<!DOCTYPE hibernate-mapping PUBLIC "-//Hibernate/Hibernate Mapping DTD 3.0//EN"
"http://hibernate.sourceforge.net/hibernate-mapping-3.0.dtd">
<!-- Mapping file autogenerated by MyEclipse Persistence Tools -->
<hibernate-mapping>
	<class name="com.teacherms.all.domain.TeacherInfo" table="teacher_info"
		catalog="pxxyteacherms">
		<id name="teacherInfoId" type="string">
			<column name="TEACHER_INFO_ID" length="40" />
			<generator class="assigned" />
		</id>
		<property name="userId" type="string">
			<column name="USER_ID" length="8">
				<comment>用户ID</comment>
			</column>
		</property>
		<property name="certificateType" type="string">
			<column name="CERTIFICATE_TYPE" length="2">
				<comment>证件类型</comment>
			</column>
		</property>
		<property name="certificateNo" type="string">
			<column name="CERTIFICATE_NO" length="20">
				<comment>证件号码</comment>
			</column>
		</property>
		<property name="nation" type="string">
			<column name="NATION" length="2">
				<comment>民族</comment>
			</column>
		</property>
		<property name="nationality" type="string">
			<column name="NATIONALITY" length="2">
				<comment>国籍</comment>
			</column>
		</property>
		<property name="GAT" type="string">
			<column name="G_A_T" length="1">
				<comment>港澳台</comment>
			</column>
		</property>
		<property name="huaQiao" type="string">
			<column name="HUA_QIAO" length="1">
				<comment>华侨</comment>
			</column>
		</property>
		<property name="politicalStatus" type="string">
			<column name="POLITICAL_STATUS" length="2">
				<comment>政治面貌</comment>
			</column>
		</property>
		<property name="sex" type="string">
			<column name="SEX" length="1">
				<comment>性别</comment>
			</column>
		</property>
		<property name="birthday" type="string">
			<column name="BIRTHDAY" length="20">
				<comment>出生年月</comment>
			</column>
		</property>
		<property name="highestEducation" type="string">
			<column name="HIGHEST_EDUCATION" length="2">
				<comment>最高学历</comment>
			</column>
		</property>
		<property name="highestDegree" type="string">
			<column name="HIGHEST_DEGREE" length="2">
				<comment>最高学位</comment>
			</column>
		</property>
		<property name="learnEdgeStructure" type="string">
			<column name="LEARN_EDGE_STRUCTURE" length="2">
				<comment>学缘</comment>
			</column>
		</property>
		<property name="professionalTitle" type="string">
			<column name="PROFESSIONAL_TITLE" length="2">
				<comment>专业技术职称</comment>
			</column>
		</property>
		<property name="professionalGrade" type="string">
			<column name="PROFESSIONAL_GRADE" length="2">
				<comment>职称级别</comment>
			</column>
		</property>
		<property name="subjectCategory" type="string">
			<column name="SUBJECT_CATEGORY" length="4">
				<comment>学科类别</comment>
			</column>
		</property>
		<property name="workDate" type="string">
			<column name="WORK_DATE" length="20">
				<comment>参加工作时间</comment>
			</column>
		</property>
		<property name="inductionDate" type="string">
			<column name="INDUCTION_DATE" length="20">
				<comment>入校时间</comment>
			</column>
		</property>
		<property name="teacherCertificateNo" type="string">
			<column name="TEACHER_CERTIFICATE_NO" length="20">
				<comment>教师资格证号</comment>
			</column>
		</property>
		<property name="teachingType" type="string">
			<column name="TEACHING_TYPE" length="20">
				<comment>授课类型</comment>
			</column>
		</property>
		<property name="teachingStatus" type="string">
			<column name="TEACHING_STATUS" length="20">
				<comment>授课状态</comment>
			</column>
		</property>
		<property name="teachingProfessionName" type="string">
			<column name="TEACHING_PROFESSION_NAME" length="20">
				<comment>任教专业名称</comment>
			</column>
		</property>
		<property name="teachingProfessionNo" type="string">
			<column name="TEACHING_PROFESSION_NO" length="6">
				<comment>任教专业代码</comment>
			</column>
		</property>
		<property name="professionTeachingDate" type="string">
			<column name="PROFESSION_TEACHING_DATE" length="20">
				<comment>专业任教时间</comment>
			</column>
		</property>
		<property name="experimentalTechnicalPersonnel" type="string">
			<column name="EXPERIMENTAL_TECHNICAL_PERSONNEL" length="1">
				<comment>是否实验技术人员</comment>
			</column>
		</property>
		<property name="doubleTeacherType" type="string">
			<column name="DOUBLE_TEACHER_TYPE" length="1">
				<comment>是否双师型</comment>
			</column>
		</property>
		<property name="engineeringBackground" type="string">
			<column name="ENGINEERING_BACKGROUND" length="1">
				<comment>是否工程背景</comment>
			</column>
		</property>
		<property name="industryBackground" type="string">
			<column name="INDUSTRY_BACKGROUND" length="1">
				<comment>是否行业背景</comment>
			</column>
		</property>
		<property name="administrativeRank" type="string">
			<column name="ADMINISTRATIVE_RANK" length="2">
				<comment>行政职务级别</comment>
			</column>
		</property>
		<property name="graduateTutorType" type="string">
			<column name="GRADUATE_TUTOR_TYPE" length="2">
				<comment>研究生导师类型</comment>
			</column>
		</property>
		<property name="numberOfDoctor" type="integer">
			<column name="NUMBER_OF_DOCTOR">
				<comment>校内指导博士生人数</comment>
			</column>
		</property>
		<property name="numberOfMaster" type="integer">
			<column name="NUMBER_OF_MASTER">
				<comment>内指导硕士生人数</comment>
			</column>
		</property>
		<property name="employeeType" type="string">
			<column name="EMPLOYEE_TYPE" length="2">
				<comment>职工类型</comment>
			</column>
		</property>
		<property name="employmentType" type="string">
			<column name="EMPLOYMENT_TYPE" length="2">
				<comment>录用类型</comment>
			</column>
		</property>
		<property name="jobStatue" type="string">
			<column name="JOB_STATUE" length="2">
				<comment>任职状态</comment>
			</column>
		</property>
		<property name="transactionType" type="string">
			<column name="TRANSACTION_TYPE" length="2">
				<comment>异动类型</comment>
			</column>
		</property>
		<property name="universityTransfer" type="string">
			<column name="UNIVERSITY_TRANSFER" length="1">
				<comment>高校调入</comment>
			</column>
		</property>
		<property name="schoolGraduation" type="string">
			<column name="SCHOOL_GRADUATION" length="1">
				<comment>本校毕业</comment>
			</column>
		</property>
		<property name="schoolAdjustment" type="string">
			<column name="SCHOOL_ADJUSTMENT" length="1">
				<comment>本校调整</comment>
			</column>
		</property>
		<property name="offCampusTeacherType" type="string">
			<column name="OFF_CAMPUS_TEACHER_TYPE" length="2">
				<comment>校外教师类型</comment>
			</column>
		</property>
		<property name="dataStatus" type="string">
			<column name="DATA_STATUS" length="2">
				<comment>数据状态</comment>
			</column>
		</property>
		<property name="createTime" type="string">
			<column name="CREATE_TIME" length="20">
				<comment>创建时间</comment>
			</column>
		</property>
	</class>
</hibernate-mapping>
